nonebot_plugin_dicky_pk/__init__.py
nonebot_plugin_dicky_pk/src/badge.py
nonebot_plugin_dicky_pk/src/badge_parser.py
nonebot_plugin_dicky_pk/src/cd.py
nonebot_plugin_dicky_pk/src/config.json
nonebot_plugin_dicky_pk/src/config.py
nonebot_plugin_dicky_pk/src/config_parser.py
nonebot_plugin_dicky_pk/src/constants.py
nonebot_plugin_dicky_pk/src/db.py
nonebot_plugin_dicky_pk/src/farm.py
nonebot_plugin_dicky_pk/src/friends.py
nonebot_plugin_dicky_pk/src/impl.py
nonebot_plugin_dicky_pk/src/main.py
nonebot_plugin_dicky_pk/src/rebirth.py
nonebot_plugin_dicky_pk/src/rebirth_view.py
nonebot_plugin_dicky_pk/src/utils.py
nonebot_plugin_dicky_pk-0.7.1.dist-info/LICENSE
nonebot_plugin_dicky_pk-0.7.1.dist-info/METADATA
nonebot_plugin_dicky_pk-0.7.1.dist-info/WHEEL
nonebot_plugin_dicky_pk-0.7.1.dist-info/RECORD
